{
  "2022-09-30T21:05:45.974Z": {
    "viewCount": "95694054",
    "likeCount": "1258705",
    "commentCount": "43935"
  },
  "2022-10-05T01:17:41.332Z": {
    "viewCount": "95836502",
    "likeCount": "1259821",
    "commentCount": "43941"
  },
  "2022-10-06T01:12:21.136Z": {
    "viewCount": "95870159",
    "likeCount": "1260088",
    "commentCount": "43950"
  },
  "2022-10-07T01:22:49.424Z": {
    "viewCount": "95903816",
    "likeCount": "1260343",
    "commentCount": "43951"
  },
  "2022-10-08T01:07:16.093Z": {
    "viewCount": "95939765",
    "likeCount": "1260575",
    "commentCount": "43949"
  },
  "2022-10-09T01:13:16.537Z": {
    "viewCount": "95977399",
    "likeCount": "1260845",
    "commentCount": "43956"
  },
  "2022-10-10T01:17:48.435Z": {
    "viewCount": "96009981",
    "likeCount": "1261060",
    "commentCount": "43946"
  },
  "2022-10-11T01:10:54.819Z": {
    "viewCount": "96041610",
    "likeCount": "1261235",
    "commentCount": "43944"
  },
  "2022-10-12T01:25:55.995Z": {
    "viewCount": "96074554",
    "likeCount": "1261439",
    "commentCount": "43950"
  },
  "2022-10-13T01:16:00.696Z": {
    "viewCount": "96105974",
    "likeCount": "1261652",
    "commentCount": "43947"
  },
  "2022-10-14T01:26:04.575Z": {
    "viewCount": "96137899",
    "likeCount": "1261853",
    "commentCount": "43952"
  },
  "2022-10-15T01:20:16.045Z": {
    "viewCount": "96168254",
    "likeCount": "1262053",
    "commentCount": "43952"
  },
  "2022-10-16T01:22:14.095Z": {
    "viewCount": "96200289",
    "likeCount": "1262251",
    "commentCount": "43956"
  },
  "2022-10-17T01:24:07.094Z": {
    "viewCount": "96226557",
    "likeCount": "1262415",
    "commentCount": "43964"
  },
  "2022-10-18T01:18:35.029Z": {
    "viewCount": "96248727",
    "likeCount": "1262540",
    "commentCount": "43965"
  },
  "2022-10-19T01:19:23.208Z": {
    "viewCount": "96273153",
    "likeCount": "1262686",
    "commentCount": "43981"
  },
  "2022-10-20T01:14:51.095Z": {
    "viewCount": "96300579",
    "likeCount": "1262863",
    "commentCount": "43979"
  },
  "2022-10-21T01:11:52.427Z": {
    "viewCount": "96325805",
    "likeCount": "1263033",
    "commentCount": "43985"
  },
  "2022-10-22T01:18:58.090Z": {
    "viewCount": "96352185",
    "likeCount": "1263240",
    "commentCount": "43989"
  },
  "2022-10-23T01:16:59.156Z": {
    "viewCount": "96381005",
    "likeCount": "1263420",
    "commentCount": "43991"
  },
  "2022-10-24T01:28:43.273Z": {
    "viewCount": "96405875",
    "likeCount": "1263578",
    "commentCount": "43996"
  },
  "2022-10-25T01:23:46.286Z": {
    "viewCount": "96430048",
    "likeCount": "1263746",
    "commentCount": "44001"
  },
  "2022-10-26T01:09:36.641Z": {
    "viewCount": "96455937",
    "likeCount": "1263893",
    "commentCount": "44004"
  },
  "2022-10-27T01:09:10.436Z": {
    "viewCount": "96482031",
    "likeCount": "1264067",
    "commentCount": "44004"
  },
  "2022-10-28T01:14:05.392Z": {
    "viewCount": "96510382",
    "likeCount": "1264241",
    "commentCount": "44007"
  },
  "2022-10-29T01:01:18.150Z": {
    "viewCount": "96541005",
    "likeCount": "1264397",
    "commentCount": "44005"
  },
  "2022-10-30T01:15:23.472Z": {
    "viewCount": "96572999",
    "likeCount": "1264593",
    "commentCount": "44013"
  },
  "2022-10-31T01:15:59.594Z": {
    "viewCount": "96601350",
    "likeCount": "1264777",
    "commentCount": "44013"
  },
  "2022-11-01T01:20:07.686Z": {
    "viewCount": "96627845",
    "likeCount": "1264932",
    "commentCount": "44014"
  },
  "2022-11-02T01:13:35.023Z": {
    "viewCount": "96654320",
    "likeCount": "1265093",
    "commentCount": "44017"
  },
  "2022-11-03T01:07:08.238Z": {
    "viewCount": "96679988",
    "likeCount": "1265235",
    "commentCount": "44029"
  },
  "2022-11-04T01:12:43.724Z": {
    "viewCount": "96706962",
    "likeCount": "1265392",
    "commentCount": "44032"
  },
  "2022-11-05T01:07:26.433Z": {
    "viewCount": "96733505",
    "likeCount": "1265589",
    "commentCount": "44036"
  },
  "2022-11-06T01:04:56.584Z": {
    "viewCount": "96759646",
    "likeCount": "1265751",
    "commentCount": "44035"
  },
  "2022-11-07T01:03:04.611Z": {
    "viewCount": "96784132",
    "likeCount": "1265924",
    "commentCount": "44037"
  },
  "2022-11-08T01:03:08.268Z": {
    "viewCount": "96807446",
    "likeCount": "1266084",
    "commentCount": "44036"
  },
  "2022-11-09T01:04:24.458Z": {
    "viewCount": "96832211",
    "likeCount": "1266183",
    "commentCount": "44036"
  },
  "2022-11-10T01:04:48.566Z": {
    "viewCount": "96856931",
    "likeCount": "1266308",
    "commentCount": "44034"
  },
  "2022-11-11T01:07:32.455Z": {
    "viewCount": "96882214",
    "likeCount": "1266478",
    "commentCount": "44033"
  },
  "2022-11-12T01:03:43.281Z": {
    "viewCount": "96909034",
    "likeCount": "1266660",
    "commentCount": "44030"
  },
  "2022-11-13T01:03:06.921Z": {
    "viewCount": "96938115",
    "likeCount": "1266830",
    "commentCount": "44030"
  },
  "2022-11-14T01:01:08.803Z": {
    "viewCount": "96964758",
    "likeCount": "1266999",
    "commentCount": "44036"
  },
  "2022-11-15T01:01:22.716Z": {
    "viewCount": "96989364",
    "likeCount": "1267158",
    "commentCount": "44029"
  },
  "2022-11-16T01:01:28.497Z": {
    "viewCount": "97016815",
    "likeCount": "1267363",
    "commentCount": "44026"
  },
  "2022-11-17T01:02:04.423Z": {
    "viewCount": "97049959",
    "likeCount": "1268010",
    "commentCount": "44046"
  },
  "2022-11-18T01:04:35.158Z": {
    "viewCount": "97105745",
    "likeCount": "1269200",
    "commentCount": "44090"
  },
  "2022-11-19T01:02:22.107Z": {
    "viewCount": "97153353",
    "likeCount": "1270035",
    "commentCount": "44129"
  },
  "2022-11-20T01:04:38.021Z": {
    "viewCount": "97206372",
    "likeCount": "1270764",
    "commentCount": "44147"
  },
  "2022-11-21T01:01:56.702Z": {
    "viewCount": "97250255",
    "likeCount": "1271302",
    "commentCount": "44156"
  },
  "2022-11-22T01:02:40.326Z": {
    "viewCount": "97289768",
    "likeCount": "1271716",
    "commentCount": "44161"
  },
  "2022-11-23T00:56:14.860Z": {
    "viewCount": "97327005",
    "likeCount": "1272083",
    "commentCount": "44167"
  },
  "2022-11-24T01:00:44.461Z": {
    "viewCount": "97364696",
    "likeCount": "1272434",
    "commentCount": "44169"
  },
  "2022-11-25T00:56:31.053Z": {
    "viewCount": "97403363",
    "likeCount": "1272767",
    "commentCount": "44173"
  },
  "2022-11-26T00:52:35.582Z": {
    "viewCount": "97443580",
    "likeCount": "1273084",
    "commentCount": "44175"
  },
  "2022-11-27T01:00:48.283Z": {
    "viewCount": "97480714",
    "likeCount": "1273378",
    "commentCount": "44173"
  },
  "2022-11-28T00:54:12.883Z": {
    "viewCount": "97514723",
    "likeCount": "1273659",
    "commentCount": "44178"
  },
  "2022-11-29T00:56:10.726Z": {
    "viewCount": "97552002",
    "likeCount": "1273997",
    "commentCount": "44177"
  },
  "2022-11-30T00:56:54.445Z": {
    "viewCount": "97588452",
    "likeCount": "1274315",
    "commentCount": "44184"
  },
  "2022-12-01T01:02:22.041Z": {
    "viewCount": "97621786",
    "likeCount": "1274662",
    "commentCount": "44193"
  },
  "2022-12-02T00:53:59.905Z": {
    "viewCount": "97658983",
    "likeCount": "1274974",
    "commentCount": "44204"
  },
  "2022-12-03T00:50:41.851Z": {
    "viewCount": "97699567",
    "likeCount": "1275259",
    "commentCount": "44209"
  },
  "2022-12-04T00:53:13.001Z": {
    "viewCount": "97737930",
    "likeCount": "1275519",
    "commentCount": "44219"
  },
  "2022-12-05T00:52:25.431Z": {
    "viewCount": "97777740",
    "likeCount": "1275783",
    "commentCount": "44218"
  },
  "2022-12-06T00:51:48.742Z": {
    "viewCount": "97813736",
    "likeCount": "1276054",
    "commentCount": "44221"
  },
  "2022-12-07T00:54:48.143Z": {
    "viewCount": "97850439",
    "likeCount": "1276287",
    "commentCount": "44222"
  },
  "2022-12-08T00:51:46.797Z": {
    "viewCount": "97888174",
    "likeCount": "1276532",
    "commentCount": "44221"
  },
  "2022-12-09T00:53:43.818Z": {
    "viewCount": "97929676",
    "likeCount": "1276753",
    "commentCount": "44220"
  },
  "2022-12-10T00:49:59.532Z": {
    "viewCount": "97962993",
    "likeCount": "1276970",
    "commentCount": "44226"
  },
  "2022-12-11T00:57:44.314Z": {
    "viewCount": "97996554",
    "likeCount": "1277185",
    "commentCount": "44226"
  },
  "2022-12-12T00:55:05.908Z": {
    "viewCount": "98030485",
    "likeCount": "1277365",
    "commentCount": "44228"
  },
  "2022-12-13T00:56:34.548Z": {
    "viewCount": "98064251",
    "likeCount": "1277562",
    "commentCount": "44223"
  },
  "2022-12-14T00:53:09.316Z": {
    "viewCount": "98093950",
    "likeCount": "1277711",
    "commentCount": "44226"
  },
  "2022-12-15T00:54:39.874Z": {
    "viewCount": "98120023",
    "likeCount": "1277874",
    "commentCount": "44223"
  },
  "2022-12-16T00:50:48.629Z": {
    "viewCount": "98151848",
    "likeCount": "1278026",
    "commentCount": "44194"
  },
  "2022-12-17T00:48:03.018Z": {
    "viewCount": "98180147",
    "likeCount": "1278185",
    "commentCount": "44194"
  },
  "2022-12-18T00:49:58.091Z": {
    "viewCount": "98208095",
    "likeCount": "1278368",
    "commentCount": "44199"
  },
  "2022-12-19T00:47:53.526Z": {
    "viewCount": "98230929",
    "likeCount": "1278489",
    "commentCount": "44202"
  },
  "2022-12-20T00:52:49.983Z": {
    "viewCount": "98255045",
    "likeCount": "1278623",
    "commentCount": "44201"
  },
  "2022-12-21T00:47:55.548Z": {
    "viewCount": "98280836",
    "likeCount": "1278730",
    "commentCount": "44209"
  },
  "2022-12-22T00:51:23.191Z": {
    "viewCount": "98308888",
    "likeCount": "1278883",
    "commentCount": "44214"
  },
  "2022-12-23T00:49:47.424Z": {
    "viewCount": "98337205",
    "likeCount": "1279021",
    "commentCount": "44216"
  },
  "2022-12-24T00:44:46.519Z": {
    "viewCount": "98364243",
    "likeCount": "1279184",
    "commentCount": "44218"
  },
  "2022-12-25T00:53:27.379Z": {
    "viewCount": "98394980",
    "likeCount": "1279337",
    "commentCount": "44221"
  },
  "2022-12-26T00:51:15.397Z": {
    "viewCount": "98419053",
    "likeCount": "1279438",
    "commentCount": "44229"
  },
  "2022-12-27T00:50:51.557Z": {
    "viewCount": "98447903",
    "likeCount": "1279577",
    "commentCount": "44231"
  },
  "2022-12-28T00:50:08.522Z": {
    "viewCount": "98472278",
    "likeCount": "1279725",
    "commentCount": "44230"
  },
  "2022-12-29T00:51:46.450Z": {
    "viewCount": "98494645",
    "likeCount": "1279866",
    "commentCount": "44236"
  },
  "2022-12-30T00:51:50.858Z": {
    "viewCount": "98520012",
    "likeCount": "1280016",
    "commentCount": "44241"
  },
  "2022-12-31T00:49:46.537Z": {
    "viewCount": "98542263",
    "likeCount": "1280160",
    "commentCount": "44239"
  },
  "2023-01-01T00:58:26.931Z": {
    "viewCount": "98570202",
    "likeCount": "1280312",
    "commentCount": "44242"
  },
  "2023-01-02T00:51:27.417Z": {
    "viewCount": "98590133",
    "likeCount": "1280411",
    "commentCount": "44237"
  },
  "2023-01-03T00:50:43.414Z": {
    "viewCount": "98611679",
    "likeCount": "1280525",
    "commentCount": "44243"
  },
  "2023-01-04T00:51:59.136Z": {
    "viewCount": "98632502",
    "likeCount": "1280622",
    "commentCount": "44244"
  },
  "2023-01-05T00:53:34.760Z": {
    "viewCount": "98655212",
    "likeCount": "1280735",
    "commentCount": "44249"
  },
  "2023-01-06T00:53:41.365Z": {
    "viewCount": "98677808",
    "likeCount": "1280844",
    "commentCount": "44254"
  },
  "2023-01-07T00:50:52.596Z": {
    "viewCount": "98702439",
    "likeCount": "1280959",
    "commentCount": "44254"
  },
  "2023-01-08T00:57:51.898Z": {
    "viewCount": "98728096",
    "likeCount": "1281060",
    "commentCount": "44254"
  },
  "2023-01-09T00:51:57.528Z": {
    "viewCount": "98752562",
    "likeCount": "1281194",
    "commentCount": "44252"
  },
  "2023-01-10T00:54:51.789Z": {
    "viewCount": "98773963",
    "likeCount": "1281312",
    "commentCount": "44255"
  },
  "2023-01-11T00:52:46.829Z": {
    "viewCount": "98788107",
    "likeCount": "1281450",
    "commentCount": "44255"
  },
  "2023-01-12T00:54:07.406Z": {
    "viewCount": "98824951",
    "likeCount": "1281820",
    "commentCount": "44265"
  },
  "2023-01-13T00:54:06.637Z": {
    "viewCount": "98896869",
    "likeCount": "1283407",
    "commentCount": "44302"
  },
  "2023-01-14T00:50:07.922Z": {
    "viewCount": "98982385",
    "likeCount": "1285652",
    "commentCount": "44385"
  },
  "2023-01-15T00:56:04.442Z": {
    "viewCount": "99064224",
    "likeCount": "1287612",
    "commentCount": "44450"
  },
  "2023-01-16T00:52:37.259Z": {
    "viewCount": "99134096",
    "likeCount": "1289030",
    "commentCount": "44490"
  },
  "2023-01-17T00:52:17.100Z": {
    "viewCount": "99206760",
    "likeCount": "1290467",
    "commentCount": "44532"
  },
  "2023-01-18T00:55:09.361Z": {
    "viewCount": "99274469",
    "likeCount": "1291649",
    "commentCount": "44578"
  },
  "2023-01-19T00:54:39.976Z": {
    "viewCount": "99354767",
    "likeCount": "1292724",
    "commentCount": "44621"
  },
  "2023-01-20T00:53:42.658Z": {
    "viewCount": "99425429",
    "likeCount": "1293633",
    "commentCount": "44649"
  },
  "2023-01-21T00:53:30.606Z": {
    "viewCount": "99498101",
    "likeCount": "1294563",
    "commentCount": "44676"
  },
  "2023-01-22T00:55:59.220Z": {
    "viewCount": "99573248",
    "likeCount": "1295397",
    "commentCount": "44706"
  },
  "2023-01-23T00:51:23.799Z": {
    "viewCount": "99637895",
    "likeCount": "1296093",
    "commentCount": "44731"
  },
  "2023-01-24T00:55:09.577Z": {
    "viewCount": "99700296",
    "likeCount": "1296671",
    "commentCount": "44752"
  },
  "2023-01-25T00:51:33.683Z": {
    "viewCount": "99762835",
    "likeCount": "1297271",
    "commentCount": "44759"
  },
  "2023-01-26T00:51:53.940Z": {
    "viewCount": "99831439",
    "likeCount": "1297847",
    "commentCount": "44787"
  },
  "2023-01-27T00:55:02.680Z": {
    "viewCount": "99903090",
    "likeCount": "1298513",
    "commentCount": "44805"
  },
  "2023-01-28T00:53:24.563Z": {
    "viewCount": "99971739",
    "likeCount": "1299154",
    "commentCount": "44833"
  },
  "2023-01-29T00:57:19.184Z": {
    "viewCount": "100035059",
    "likeCount": "1299781",
    "commentCount": "44916"
  },
  "2023-01-30T00:49:29.065Z": {
    "viewCount": "100092440",
    "likeCount": "1300285",
    "commentCount": "44961"
  },
  "2023-01-31T00:55:41.858Z": {
    "viewCount": "100147867",
    "likeCount": "1300766",
    "commentCount": "44987"
  },
  "2023-02-01T00:59:43.298Z": {
    "viewCount": "100203693",
    "likeCount": "1301248",
    "commentCount": "45019"
  },
  "2023-02-02T00:53:59.171Z": {
    "viewCount": "100259200",
    "likeCount": "1301781",
    "commentCount": "45048"
  },
  "2023-02-03T00:55:59.558Z": {
    "viewCount": "100317308",
    "likeCount": "1302213",
    "commentCount": "45070"
  },
  "2023-02-04T00:51:42.303Z": {
    "viewCount": "100374968",
    "likeCount": "1302619",
    "commentCount": "45086"
  },
  "2023-02-05T00:57:58.550Z": {
    "viewCount": "100431325",
    "likeCount": "1303041",
    "commentCount": "45095"
  },
  "2023-02-06T00:51:47.793Z": {
    "viewCount": "100482262",
    "likeCount": "1303441",
    "commentCount": "45108"
  },
  "2023-02-07T00:53:31.515Z": {
    "viewCount": "100535055",
    "likeCount": "1303791",
    "commentCount": "45121"
  },
  "2023-02-08T00:54:33.066Z": {
    "viewCount": "100590190",
    "likeCount": "1304168",
    "commentCount": "45125"
  }
}